{
  "id": "shared/api/client.ts:ApiClientConfig",
  "name": "ApiClientConfig",
  "source": "interface ApiClientConfig {\n  baseURL: string\n  timeout?: number\n  getToken?: GetToken\n}",
  "target": "Σ ApiClientConfig {\n    baseURL: String,\n    timeout?: f64,\n    getToken?: GetToken\n}",
  "manual_review_needed": false,
  "notes": [],
  "fields": [
    {
      "name": "baseURL",
      "type_annotation": "string",
      "optional": false,
      "readonly": false,
      "type_kind": "primitive:string"
    },
    {
      "name": "timeout",
      "type_annotation": "number",
      "optional": true,
      "readonly": false,
      "type_kind": "primitive:number"
    },
    {
      "name": "getToken",
      "type_annotation": "GetToken",
      "optional": true,
      "readonly": false,
      "type_kind": "ref:GetToken"
    }
  ]
}